logfly/__init__.py
logfly-2.5.dist-info/LICENSE
logfly-2.5.dist-info/METADATA
logfly-2.5.dist-info/WHEEL
logfly-2.5.dist-info/top_level.txt
logfly-2.5.dist-info/RECORD
