Metadata-Version: 2.1
Name: logfly
Version: 2.5
Summary: A simple log tool by python
Home-page: https://about.guki.me
Author: Yuan Sui
Author-email: orisui@icloud.com
Project-URL: Github, https://github.com/tinqlo/logfly
Classifier: Programming Language :: Python :: 3
Classifier: License :: OSI Approved :: MIT License
Classifier: Operating System :: OS Independent
Requires-Python: >=3.6
License-File: LICENSE
Requires-Dist: colorama
